fulladder/fulladder.v
module fulladder(A,B,C,sum,co);
 input A,B,C;
 output sum,co;
//wire w1,w2,w3;

xor g1(w1,A,B),
    g2(sum,C,w1),g5(co,w2,w3);
and g3(w2,A,B),
    g4(w3,C,w1);    

//instantiate (.bottom(top), .bott(top))

//andg1 g3(.C(w2),.A(A),.B(B)),
//      g4(.C(w3),.A(C),.B(w1));


endmodule

//module andg1(A,B,C);
//input A,B;
//output C;

//and g6(C,A,B);

//endmodule

fa_tb.v
module fa_tb();
reg A=0,B=0,C=0;
wire sum, co;
fulladder f1(.A(A),.B(B),.C(C),.sum(sum),.co(co));
integer i;
initial 
    begin
	$dumpfile ("fa.vcd");
	$dumpvars (0,fa_tb);
	$display ("\t\tTime\tA\tB\tC\tsum\tcout");
	$monitor ($time,"\t%b\t%b\t%b\t%b\t%b",A,B,C,sum,co);
	//#40 $finish;
    
    // using for loop 
    for (i=0;i<8;i=i+1)
    begin
    	{A,B,C}=i;
    	#10;
    end
    end
    
    // using always block
	/*always 
        #20 A = ~A;
        always
        #10 B = ~B;
        always
        #5 C = ~C;*/
endmodule

fulladder/fa.vcd
$date
	Sat Jan 14 23:48:24 2023
$end
$version
	Icarus Verilog
$end
$timescale
	1s
$end
$scope module fa_tb $end
$var wire 1 ! sum $end
$var wire 1 " co $end
$var reg 1 # A $end
$var reg 1 $ B $end
$var reg 1 % C $end
$var integer 32 & i [31:0] $end
$scope module f1 $end
$var wire 1 # A $end
$var wire 1 $ B $end
$var wire 1 % C $end
$var wire 1 " co $end
$var wire 1 ! sum $end
$var wire 1 ' w1 $end
$var wire 1 ( w2 $end
$var wire 1 ) w3 $end
$upscope $end
$upscope $end
$enddefinitions $end
#0
$dumpvars
0)
0(
0'
b0 &
0%
0$
0#
0"
0!
$end
#10
1!
1%
b1 &
#20
1'
1!
1$
0%
b10 &
#30
1"
0!
1)
1%
b11 &
#40
0"
1!
0)
1#
0$
0%
b100 &
#50
1"
0!
1)
1%
b101 &
#60
0'
1(
0!
0)
1$
0%
b110 &
#70
1!
1%
b111 &
#80
b1000 &
